endur-0.0.1.dist-info/METADATA
endur-0.0.1.dist-info/WHEEL
endur-0.0.1.dist-info/licenses/LICENSE
endur/__init__.py
endur/endur.cpython-313-darwin.so
endur-0.0.1.dist-info/RECORD
